libmytoken/__init__.py
libmytoken/accesstoken.py
libmytoken/error.py
libmytoken/from_jwt.py
libmytoken/server.py
libmytoken-0.1.0.dist-info/LICENSE
libmytoken-0.1.0.dist-info/METADATA
libmytoken-0.1.0.dist-info/WHEEL
libmytoken-0.1.0.dist-info/top_level.txt
libmytoken-0.1.0.dist-info/RECORD
