Metadata-Version: 2.1
Name: libmytoken
Version: 0.1.0
Summary: A python library for interacting with a mytoken server.
Home-page: https://github.com/oidc-mytoken/libpy
Author: Gabriel Zachmann
Author-email: mytoken-contact@lists.kit.edu
License: MIT
Project-URL: Source, https://github.com/oidc-mytoken/libpy
Project-URL: Bug Tracker, https://github.com/oidc-mytoken/libpy/issues
Project-URL: Documentation, https://mytoken-docs.data.kit.edu
Classifier: License :: OSI Approved :: MIT License
Classifier: Programming Language :: Python
Classifier: Programming Language :: Python :: 3
Classifier: Programming Language :: Python :: 3.4
Classifier: Programming Language :: Python :: 3.5
Classifier: Programming Language :: Python :: 3.6
Classifier: Programming Language :: Python :: 3.7
Classifier: Programming Language :: Python :: 3.8
Classifier: Programming Language :: Python :: 3.9
Classifier: Programming Language :: Python :: 3.10
Classifier: Programming Language :: Python :: 3.11
Classifier: Topic :: System :: Systems Administration :: Authentication/Directory
Classifier: Topic :: Utilities
Classifier: Topic :: Security
Classifier: Topic :: Software Development :: Libraries
Classifier: Intended Audience :: Developers
Classifier: Intended Audience :: Information Technology
Classifier: Intended Audience :: Science/Research
Classifier: Intended Audience :: System Administrators
Classifier: Environment :: Console
Classifier: Natural Language :: English
License-File: LICENSE
